deutschland/coachingangebote/__init__.py
deutschland/coachingangebote/api/__init__.py
deutschland/coachingangebote/api/default_api.py
deutschland/coachingangebote/api_client.py
deutschland/coachingangebote/apis/__init__.py
deutschland/coachingangebote/configuration.py
deutschland/coachingangebote/exceptions.py
deutschland/coachingangebote/model/__init__.py
deutschland/coachingangebote/model/response.py
deutschland/coachingangebote/model/response_aggregations.py
deutschland/coachingangebote/model/response_aggregations_anzahlausgefiltert.py
deutschland/coachingangebote/model/response_aggregations_anzahlgesamt.py
deutschland/coachingangebote/model/response_aggregations_regionen.py
deutschland/coachingangebote/model/response_aggregations_unterrichsformen.py
deutschland/coachingangebote/model/response_embedded.py
deutschland/coachingangebote/model/response_embedded_abstaende.py
deutschland/coachingangebote/model/response_embedded_adresse.py
deutschland/coachingangebote/model/response_embedded_angebot.py
deutschland/coachingangebote/model/response_embedded_angebot_anbieter.py
deutschland/coachingangebote/model/response_embedded_angebot_anbieter_adresse.py
deutschland/coachingangebote/model/response_embedded_angebot_anbieter_adresse_ort_strasse.py
deutschland/coachingangebote/model/response_embedded_angebot_anbieter_adresse_ort_strasse_koordinaten.py
deutschland/coachingangebote/model/response_embedded_angebot_anbieter_adresse_ort_strasse_land.py
deutschland/coachingangebote/model/response_embedded_angebot_anbieter_logo.py
deutschland/coachingangebote/model/response_embedded_angebot_suchworte.py
deutschland/coachingangebote/model/response_embedded_angebot_systematiken.py
deutschland/coachingangebote/model/response_embedded_angebot_zertifizierer.py
deutschland/coachingangebote/model/response_embedded_ansprechpartner.py
deutschland/coachingangebote/model/response_embedded_ort.py
deutschland/coachingangebote/model/response_embedded_rollen.py
de_coachingangebote-0.1.0.dist-info/WHEEL
de_coachingangebote-0.1.0.dist-info/METADATA
de_coachingangebote-0.1.0.dist-info/RECORD
